binary_bci2000_processing/BinaryBciSignalProcessing.py
binary_bci2000_processing/Preprocessing.py
binary_bci2000_processing/SignalManager.py
binary_bci2000_processing/__init__.py
binary_bci2000_processing-1.0.1.dist-info/LICENSE
binary_bci2000_processing-1.0.1.dist-info/METADATA
binary_bci2000_processing-1.0.1.dist-info/WHEEL
binary_bci2000_processing-1.0.1.dist-info/top_level.txt
binary_bci2000_processing-1.0.1.dist-info/RECORD
