Metadata-Version: 2.1
Name: binary-bci2000-processing
Version: 1.0.1
Summary: Binary Processing
Home-page: https://github.com/s-n-1-0/binary-bci2000-processing
Download-URL: https://github.com/s-n-1-0/binary-bci2000-processing
Author: sn-10
License: MIT
License-File: LICENSE
